Workbook

Sheet 00_Об_этой_версии
A1: Бизнес-план El Lavash
A2: Реалистичный сценарий — команда из 3 (Элен + 2 сотрудника), малое артизан-производство.
A4: Ключевые параметры:
A5: Производство месяц 1: 200 кг (8 кг/день × 26 дней)
A6: Производство месяц 12: 500 кг (19 кг/день × 26 дней)
A7: Опт €5,50/кг, розница €8,00/кг (диапазон €7-9), себестоимость €1,55/кг
A8: OpEx ~€1000-1500/мес (аренда €800, газ/комм €200, прочее)
A9: Год 1 выручка ориентир: €20-30 тыс
A10: Точка безубыточности: 12-20 кг/день
A11: Команда: Элен + 2 сотрудника (Украина, опыт с полуфабрикатами)
A13: Каналы года 1:
A14: Локальная розница Льорет (Наш магазин, армянские ресторанчики — уже договорено)
... A25: Откройте в Excel один раз чтобы формулы пересчитались.

Sheet 13_Dashboard
A1: DASHBOARD — El Lavash Business Plan
A3: Метрика | B3: Пессимизм | C3: Реализм | D3: Супер-опт | E3: Источник | F3: Комментарий
A4: Объём год 1 (кг) | B4: ='04_Production Ramp'!B17 -> 13950 | C4: ='04_Production Ramp'!C17 -> 23550 | D4: ='04_Production Ramp'!D17 -> 43800 | E4: Production Ramp | F4: Сумма помесячных объёмов
A5: Ср.цена €/кг | B5: ='03_Sales Mix'!C12 -> 6.125 | C5: ='03_Sales Mix'!D12 -> 5.655 | D5: ='03_Sales Mix'!E12 -> 5.125 | E5: Sales Mix | F5: Взвешенная по каналам
A6: Выручка год 1 (€) | B6: ='07_PL Пессимизм'!D16 -> 85443.75 | C6: ='08_PL Реализм'!D16 -> 133175.25 | D6: ='09_PL Суперопт'!D16 -> 224475 | E6: P&L | F6: Сумма помесячная
A7: EBITDA год 1 (€) | B7: ='07_PL Пессимизм'!G16 -> 13373.832 | C7: ='08_PL Реализм'!G16 -> 59917.932 | D7: ='09_PL Суперопт'!G16 -> 132199.18 | E7: P&L | F7: Прибыль до амортизации
A8: EBITDA margin % | B8: =B7/B6 -> 0.15652206 | C8: =C7/C6 -> 0.44991792 | D8: =D7/D6 -> 0.58892608 | E8: Calc | F8: EBITDA / Revenue
A9: Break-even кг/день | B9: ='10_Break-even'!B9 -> 35.415324 | C9: ='10_Break-even'!C9 -> 29.104374 | D9: ='10_Break-even'!D9 -> 23.044453 | E9: Break-even | F9: OPEX / маржа / 26 дней
A10: CAPEX (старт) | B10: ='06_CAPEX'!B15 -> 24414.25 | C10: ='06_CAPEX'!B15 -> 24414.25 | D10: ='06_CAPEX'!B15 -> 24414.25 | E10: CAPEX | F10: Все стартовые расходы
A12: ВАЖНО:
A13: 1. Все цифры рассчитаны формулами — меняй Inputs или Production Ramp, всё пересчитается.
A14: 2. Объёмы 4 400+ кг/мес в Реализме могут быть оптимистичными для 1 спирального тестомеса + 2 работника.
A15: 3. Без подтверждения мощности печи Helen — это математическая модель, не операционный план.
A16: 4. Halal-сертификат добавит +30% объёма (марокканский канал) — отражено в Супер-опт.
A17: 5. Каждая цифра в Inputs имеет источник в колонке E. Проверяй там.

Sheet 01_Inputs
A1: ВХОДНЫЕ ПАРАМЕТРЫ — ИСТОЧНИКИ И ЦЕНЫ
A3: # | B3: Параметр | C3: Значение | D3: Ед. | E3: Источник | F3: Статус
A4: 1 | B4: Мука W-260 опт | C4: 0.75 | D4: €/кг | E4: B-Grup / Selina Wamucii | F4: estimate
A5: 2 | B5: Дрожжи свежие опт | C5: 2.5 | D5: €/кг | E5: Codipán / AB Mauri | F5: estimate
A6: 3 | B6: Соль промышленная | C6: 0.4 | D6: €/кг | E6: Sal Costa B2B | F6: estimate
A7: 4 | B7: Вода питьевая | C7: 0.003 | D7: €/л | E7: Aqualia Льорет | F7: estimate
A8: 5 | B8: Электричество PYME | C8: 0.12 | D8: €/кВт·ч | E8: Roams / Octopus 2026 | F8: verified
A9: 6 | B9: Электр. на 1 кг лаваша | C9: 0.8 | D9: кВт·ч/кг | E9: Maeswell обrador baseline | F9: estimate
A10: 7 | B10: Газ природный PYME | C10: 200 | D10: €/кВт·ч | E10: TodoLuzYGas май 2026 | F10: verified
A11: 8 | B11: Пакет OPP 400 г | C11: 0.03 | D11: €/шт | E11: B2B типография Каталония | F11: estimate
A12: 9 | B12: Этикетка с EAN/печатью | C12: 0.05 | D12: €/шт | E12: B2B Каталония | F12: estimate
A13: 10 | B13: SMI 2026 brutto/мес | C13: 1221 | D13: € | E13: BOE-A-2026-3815 / La Moncloa | F13: verified
A14: 11 | B14: Соц.отчисления работодателя | C14: 0.3215 | D14: доля от gross | E14: Seg.Social 2026 | F14: verified
A15: 12 | B15: ЗП пекаря gross/мес | C15: 1500 | D15: € | E15: Convenio + market | F15: estimate
... A38: 35 | B38: Подушка оборотных средств | C38: 15000 | D38: € | E38: 2 мес OPEX | F38: estimate

Sheet 02_Unit Economics
A1: UNIT ECONOMICS — Себестоимость 1 кг лаваша
A3: Ингредиент / расход | B3: Расход на 1 кг | C3: Цена единицы | D3: Стоимость €/кг | E3: Источник в Inputs
A4: Мука | B4: 0.7 | C4: ='01_Inputs'!C4 -> 0.75 | D4: =B4*C4 -> 0.525 | E4: Мука W-260 опт
A5: Дрожжи свежие | B5: 0.012 | C5: ='01_Inputs'!C5 -> 2.5 | D5: =B5*C5 -> 0.03 | E5: Дрожжи свежие опт
A6: Соль | B6: 0.012 | C6: ='01_Inputs'!C6 -> 0.4 | D6: =B6*C6 -> 0.0048 | E6: Соль промышленная
A7: Вода (на 0,4 л) | B7: 0.4 | C7: ='01_Inputs'!C7 -> 0.003 | D7: =B7*C7 -> 0.0012 | E7: Вода питьевая
A8: Электричество | B8: 0.8 | C8: ='01_Inputs'!C8 -> 0.12 | D8: =B8*C8 -> 0.096 | E8: Электричество PYME
C9: ИТОГО сырьё+энергия (COGS) | D9: =SUM(D4:D8) -> 0.657
A10: Упаковка пакет (на 2,5 ед/кг) | B10: 2.5 | C10: ='01_Inputs'!C11 -> 0.03 | D10: =B10*C10 -> 0.075 | E10: Пакет OPP 400 г
A11: Этикетка (на 2,5 ед/кг) | B11: 2.5 | C11: ='01_Inputs'!C12 -> 0.05 | D11: =B11*C11 -> 0.125 | E11: Этикетка
C12: ИТОГО Variable cost (COGS + упак.) | D12: =SUM(D4:D11) -> 1.514
A14: ЦЕНЫ ПО КАНАЛАМ
A15: Канал | B15: Цена €/кг | C15: Без IVA 4% | D15: Маржа €/кг | E15: Маржа %
A16: Опт-HORECA дистрибьютор | B16: 4.5 | C16: =B16/(1+'01_Inputs'!C18) -> 4.3269231 | D16: =C16-'02_Unit Economics'!$D$12 -> 2.8129231 | E16: =D16/B16 -> 0.62509402
A17: Розница магазин (русский/халяль) | B17: 6 | C17: =B17/(1+'01_Inputs'!C18) -> 5.7692308 | D17: =C17-'02_Unit Economics'!$D$12 -> 4.2552308 | E17: =D17/B17 -> 0.70920513
A18: Кебаб / ливанский ресторан | B18: 5.5 | C18: =B18/(1+'01_Inputs'!C18) -> 5.2884615 | D18: =C18-'02_Unit Economics'!$D$12 -> 3.7744615 | E18: =D18/B18 -> 0.68626573
A19: Отель 4-5★ Коста-Брава | B19: 6.5 | C19: =B19/(1+'01_Inputs'!C18) -> 6.25 | D19: =C19-'02_Unit Economics'!$D$12 -> 4.736 | E19: =D19/B19 -> 0.72861538
A20: Premium retail (Bonpreu KM0) | B20: 7 | C20: =B20/(1+'01_Inputs'!C18) -> 6.7307692 | D20: =C20-'02_Unit Economics'!$D$12 -> 5.2167692 | E20: =D20/B20 -> 0.74525275
A21: B2C через Glovo / прямая | B21: 10 | C21: =B21/(1+'01_Inputs'!C18) -> 9.6153846 | D21: =C21-'02_Unit Economics'!$D$12 -> 8.1013846 | E21: =D21/B21 -> 0.81013846

Sheet 03_Sales Mix
A1: МИКС КАНАЛОВ ПРОДАЖ — 3 сценария
A3: Канал | B3: Цена €/кг (Unit Econ) | C3: Пессимизм % | D3: Реализм % | E3: Супероптимизм %
A4: Опт-HORECA дистрибьютор | B4: ='02_Unit Economics'!B16 -> 4.5 | C4: 0.1 | D4: 0.2 | E4: 0.3
A5: Розница магазин (русский/халяль) | B5: ='02_Unit Economics'!B17 -> 6 | C5: 0.45 | D5: 0.3 | E5: 0.2
A6: Кебаб / ливанский ресторан | B6: ='02_Unit Economics'!B18 -> 5.5 | C6: 0.3 | D6: 0.25 | E6: 0.2
A7: Отель 4-5★ Коста-Брава | B7: ='02_Unit Economics'!B19 -> 6.5 | C7: 0.05 | D7: 0.12 | E7: 0.15
A8: Premium retail (Bonpreu KM0) | B8: ='02_Unit Economics'!B20 -> 7 | C8: 0 | D8: 0 | E8: 0
A9: B2C через Glovo / прямая | B9: ='02_Unit Economics'!B21 -> 10 | C9: 0.1 | D9: 0.08 | E9: 0.05
B10: СУММА % | C10: =SUM(C4:C9) -> 1 | D10: =SUM(D4:D9) -> 0.95 | E10: =SUM(E4:E9) -> 0.9
A12: Средневзвешенная цена €/кг | C12: =SUMPRODUCT(B4:B9,C4:C9) -> 6.125 | D12: =SUMPRODUCT(B4:B9,D4:D9) -> 5.655 | E12: =SUMPRODUCT(B4:B9,E4:E9) -> 5.125

Sheet 04_Production Ramp
A1: ОБЪЁМ ПРОИЗВОДСТВА — 12 МЕСЯЦЕВ × 3 СЦЕНАРИЯ
A4: Месяц | B4: Кг/мес ПЕССИМ | C4: Кг/мес РЕАЛИЗМ | D4: Кг/мес СУПЕР-ОПТ | E4: Комментарий
A5: M1 Setup | B5: 150 | C5: 250 | D5: 500 | E5: RSIPAC получен, первые продажи
A6: M2 | B6: 300 | C6: 500 | D6: 900 | E6: Лёлёкат разогрев
A7: M3 | B7: 500 | C7: 900 | D7: 1500 | E7: Льорет full активность
A8: M4 | B8: 700 | C8: 1300 | D8: 2200 | E8: Глово/UberEats запущены
A9: M5 BE-Realism | B9: 900 | C9: 1500 | D9: 2800 | E9: Реализм break-even
A10: M6 | B10: 1100 | C10: 1800 | D10: 3500 | E10: Halal активирован
A11: M7 Q3 | B11: 1300 | C11: 2200 | D11: 4200 | E11: HORECA контракты
A12: M8 | B12: 1500 | C12: 2500 | D12: 4800 | E12: Барселона расширение
A13: M9 | B13: 1700 | C13: 2800 | D13: 5400 | E13: Bonpreu KM0 пилот
A14: M10 | B14: 1850 | C14: 3050 | D14: 5800 | E14: Отели сезон
A15: M11 | B15: 1950 | C15: 3250 | D15: 6000 | E15: Стабилизация
A16: M12 | B16: 2000 | C16: 3500 | D16: 6200 | E16: Готовы к scale
A17: ИТОГО год 1 (кг) | B17: =SUM(B5:B16) -> 13950 | C17: =SUM(C5:C16) -> 23550 | D17: =SUM(D5:D16) -> 43800
A18: В среднем кг/день (6 раб.дн/нед) | B18: =B17/12/26 -> 44.711538 | C18: =C17/12/26 -> 75.480769 | D18: =D17/12/26 -> 140.38462 | E18: 26 раб.дней/мес

Sheet 05_OPEX Monthly
A1: OPEX — Фиксированные ежемесячные расходы
A3: Статья | B3: Пессимизм €/мес | C3: Реализм €/мес | D3: Супер-опт €/мес
A4: ЗП Элен (директор) | B4: ='01_Inputs'!C17*(1+'01_Inputs'!C14) -> 0 | C4: ='01_Inputs'!C17*(1+'01_Inputs'!C14) -> 0 | D4: ='01_Inputs'!C17*(1+'01_Inputs'!C14) -> 0
A5: ЗП пекарь 1 | B5: ='01_Inputs'!C15*(1+'01_Inputs'!C14) -> 1982.25 | C5: 0 | D5: 0
A6: ЗП помощник 1 | B6: ='01_Inputs'!C16*(1+'01_Inputs'!C14) -> 1613.5515 | C6: ='01_Inputs'!C16*(1+'01_Inputs'!C14) -> 1613.5515 | D6: ='01_Inputs'!C16*(1+'01_Inputs'!C14) -> 1613.5515
A7: Cuota autónomo Элен | B7: ='01_Inputs'!C19 -> 80 | C7: ='01_Inputs'!C19 -> 80 | D7: ='01_Inputs'!C19 -> 80
A8: Электричество | B8: 470 | C8: 550 | D8: 650
A9: Газ | B9: 0 | C9: 150 | D9: 200
A10: Вода и канализация | B10: 60 | C10: 85 | D10: 120
A11: Internet + телефон | B11: ='01_Inputs'!C21 -> 70 | C11: ='01_Inputs'!C21 -> 70 | D11: ='01_Inputs'!C21 -> 70
A12: Asesoría fiscal | B12: ='01_Inputs'!C20 -> 300 | C12: ='01_Inputs'!C20 -> 300 | D12: ='01_Inputs'!C20 -> 300
A13: Страхование RC | B13: ='01_Inputs'!C22 -> 100 | C13: ='01_Inputs'!C22 -> 100 | D13: 150
A14: SMM-менеджер | B14: 250 | C14: ='01_Inputs'!C23 -> 350 | D14: 500
A15: Логистика | B15: 200 | C15: ='01_Inputs'!C24 -> 300 | D15: 400
A16: Hygiene supplies | B16: 80 | C16: ='01_Inputs'!C25 -> 100 | D16: 120
A17: Амортизация помещения | B17: ='01_Inputs'!C26 -> 100 | C17: ='01_Inputs'!C26 -> 100 | D17: ='01_Inputs'!C26 -> 100
A18: Прочие (банк, услуги) | B18: 100 | C18: ='01_Inputs'!C27 -> 120 | D18: 150
A19: ИТОГО OPEX/мес | B19: =SUM(B4:B18) -> 4245.8015 | C19: =SUM(C4:C18) -> 3133.5515 | D19: =SUM(D4:D18) -> 2163.5515

Sheet 06_CAPEX
A1: CAPEX + СТАРТОВЫЕ РАСХОДЫ
A3: Статья | B3: Сумма € | C3: Когда | D3: Источник
A4: Constitución SL | B4: ='01_Inputs'!C28 -> 400 | C4: M0 | D4: Notario+Registro
A5: RSIPAC регистрация | B5: ='01_Inputs'!C29 -> 64.25 | C5: M0 | D5: Gencat
A6: RGSEAA + Licencia | B6: ='01_Inputs'!C30 -> 350 | C6: M1 | D6: AESAN + Ajunt.
A7: HACCP консультант | B7: ='01_Inputs'!C31 -> 500 | C7: M1 | D7: Ambialia
A8: EAN регистрация GS1 | B8: ='01_Inputs'!C32 -> 200 | C8: M1 | D8: GS1 Spain
A9: Halal-сертификат (опционально) | B9: ='01_Inputs'!C33 -> 2500 | C9: M2-M4 | D9: Instituto Halal
A10: Дизайн логотипа + упаковки | B10: ='01_Inputs'!C34 -> 800 | C10: M1 | D10: Фрилансер
A11: Печать упаковки стартовая партия | B11: ='01_Inputs'!C35 -> 1000 | C11: M1-M2 | D11: B2B
A12: Food photography | B12: ='01_Inputs'!C36 -> 600 | C12: M2 | D12: Local
A13: Резерв на оборудование/ремонт | B13: ='01_Inputs'!C37 -> 3000 | C13: M1-M3 | D13: [estimate]
A14: Подушка оборотных средств | B14: ='01_Inputs'!C38 -> 15000 | C14: M0 | D14: 2 мес OPEX
A15: ИТОГО CAPEX | B15: =SUM(B4:B14) -> 24414.25

Sheet 07_PL Пессимизм
A1: P&L 12 МЕСЯЦЕВ — ПЕССИМИСТИЧЕСКИЙ
A3: Месяц | B3: Кг/мес | C3: Ср.цена €/кг | D3: Выручка € | E3: Variable cost € | F3: OPEX € | G3: EBITDA € | H3: Накоп. EBITDA €
A4: ="M"&1 -> M1 | B4: ='04_Production Ramp'!B5 -> 150 | C4: ='03_Sales Mix'!C12 -> 6.125 | D4: =B4*C4 -> 918.75 | E4: =B4*'02_Unit Economics'!$D$12 -> 227.1 | F4: ='05_OPEX Monthly'!B19 -> 4245.8015 | G4: =D4-E4-F4 -> -3554.1515 | H4: =G4 -> -3554.1515
A5: ="M"&2 -> M2 | B5: ='04_Production Ramp'!B6 -> 300 | C5: ='03_Sales Mix'!C12 -> 6.125 | D5: =B5*C5 -> 1837.5 | E5: =B5*'02_Unit Economics'!$D$12 -> 454.2 | F5: ='05_OPEX Monthly'!B19 -> 4245.8015 | G5: =D5-E5-F5 -> -2862.5015 | H5: =H4+G5 -> -6416.653
A6: ="M"&3 -> M3 | B6: ='04_Production Ramp'!B7 -> 500 | C6: ='03_Sales Mix'!C12 -> 6.125 | D6: =B6*C6 -> 3062.5 | E6: =B6*'02_Unit Economics'!$D$12 -> 757 | F6: ='05_OPEX Monthly'!B19 -> 4245.8015 | G6: =D6-E6-F6 -> -1940.3015 | H6: =H5+G6 -> -8356.9545
A7: ="M"&4 -> M4 | B7: ='04_Production Ramp'!B8 -> 700 | C7: ='03_Sales Mix'!C12 -> 6.125 | D7: =B7*C7 -> 4287.5 | E7: =B7*'02_Unit Economics'!$D$12 -> 1059.8 | F7: ='05_OPEX Monthly'!B19 -> 4245.8015 | G7: =D7-E7-F7 -> -1018.1015 | H7: =H6+G7 -> -9375.056
A8: ="M"&5 -> M5 | B8: ='04_Production Ramp'!B9 -> 900 | C8: ='03_Sales Mix'!C12 -> 6.125 | D8: =B8*C8 -> 5512.5 | E8: =B8*'02_Unit Economics'!$D$12 -> 1362.6 | F8: ='05_OPEX Monthly'!B19 -> 4245.8015 | G8: =D8-E8-F8 -> -95.9015 | H8: =H7+G8 -> -9470.9575
A9: ="M"&6 -> M6 | B9: ='04_Production Ramp'!B10 -> 1100 | C9: ='03_Sales Mix'!C12 -> 6.125 | D9: =B9*C9 -> 6737.5 | E9: =B9*'02_Unit Economics'!$D$12 -> 1665.4 | F9: ='05_OPEX Monthly'!B19 -> 4245.8015 | G9: =D9-E9-F9 -> 826.2985 | H9: =H8+G9 -> -8644.659
A10: ="M"&7 -> M7 | B10: ='04_Production Ramp'!B11 -> 1300 | C10: ='03_Sales Mix'!C12 -> 6.125 | D10: =B10*C10 -> 7962.5 | E10: =B10*'02_Unit Economics'!$D$12 -> 1968.2 | F10: ='05_OPEX Monthly'!B19 -> 4245.8015 | G10: =D10-E10-F10 -> 1748.4985 | H10: =H9+G10 -> -6896.1605
A11: ="M"&8 -> M8 | B11: ='04_Production Ramp'!B12 -> 1500 | C11: ='03_Sales Mix'!C12 -> 6.125 | D11: =B11*C11 -> 9187.5 | E11: =B11*'02_Unit Economics'!$D$12 -> 2271 | F11: ='05_OPEX Monthly'!B19 -> 4245.8015 | G11: =D11-E11-F11 -> 2670.6985 | H11: =H10+G11 -> -4225.462
A12: ="M"&9 -> M9 | B12: ='04_Production Ramp'!B13 -> 1700 | C12: ='03_Sales Mix'!C12 -> 6.125 | D12: =B12*C12 -> 10412.5 | E12: =B12*'02_Unit Economics'!$D$12 -> 2573.8 | F12: ='05_OPEX Monthly'!B19 -> 4245.8015 | G12: =D12-E12-F12 -> 3592.8985 | H12: =H11+G12 -> -632.5635
A13: ="M"&10 -> M10 | B13: ='04_Production Ramp'!B14 -> 1850 | C13: ='03_Sales Mix'!C12 -> 6.125 | D13: =B13*C13 -> 11331.25 | E13: =B13*'02_Unit Economics'!$D$12 -> 2800.9 | F13: ='05_OPEX Monthly'!B19 -> 4245.8015 | G13: =D13-E13-F13 -> 4284.5485 | H13: =H12+G13 -> 3651.985
A14: ="M"&11 -> M11 | B14: ='04_Production Ramp'!B15 -> 1950 | C14: ='03_Sales Mix'!C12 -> 6.125 | D14: =B14*C14 -> 11943.75 | E14: =B14*'02_Unit Economics'!$D$12 -> 2952.3 | F14: ='05_OPEX Monthly'!B19 -> 4245.8015 | G14: =D14-E14-F14 -> 4745.6485 | H14: =H13+G14 -> 8397.6335
A15: ="M"&12 -> M12 | B15: ='04_Production Ramp'!B16 -> 2000 | C15: ='03_Sales Mix'!C12 -> 6.125 | D15: =B15*C15 -> 12250 | E15: =B15*'02_Unit Economics'!$D$12 -> 3028 | F15: ='05_OPEX Monthly'!B19 -> 4245.8015 | G15: =D15-E15-F15 -> 4976.1985 | H15: =H14+G15 -> 13373.832
A16: Год 1 ИТОГО | B16: =SUM(B4:B15) -> 13950 | D16: =SUM(D4:D15) -> 85443.75 | E16: =SUM(E4:E15) -> 21120.3 | F16: =SUM(F4:F15) -> 50949.618 | G16: =SUM(G4:G15) -> 13373.832 | H16: =H15 -> 13373.832

Sheet 08_PL Реализм
A1: P&L 12 МЕСЯЦЕВ — РЕАЛИСТИЧНЫЙ
A3: Месяц | B3: Кг/мес | C3: Ср.цена €/кг | D3: Выручка € | E3: Variable cost € | F3: OPEX € | G3: EBITDA € | H3: Накоп. EBITDA €
A4: ="M"&1 -> M1 | B4: ='04_Production Ramp'!C5 -> 250 | C4: ='03_Sales Mix'!D12 -> 5.655 | D4: =B4*C4 -> 1413.75 | E4: =B4*'02_Unit Economics'!$D$12 -> 378.5 | F4: ='05_OPEX Monthly'!C19 -> 3133.5515 | G4: =D4-E4-F4 -> -2098.3015 | H4: =G4 -> -2098.3015
A5: ="M"&2 -> M2 | B5: ='04_Production Ramp'!C6 -> 500 | C5: ='03_Sales Mix'!D12 -> 5.655 | D5: =B5*C5 -> 2827.5 | E5: =B5*'02_Unit Economics'!$D$12 -> 757 | F5: ='05_OPEX Monthly'!C19 -> 3133.5515 | G5: =D5-E5-F5 -> -1063.0515 | H5: =H4+G5 -> -3161.353
A6: ="M"&3 -> M3 | B6: ='04_Production Ramp'!C7 -> 900 | C6: ='03_Sales Mix'!D12 -> 5.655 | D6: =B6*C6 -> 5089.5 | E6: =B6*'02_Unit Economics'!$D$12 -> 1362.6 | F6: ='05_OPEX Monthly'!C19 -> 3133.5515 | G6: =D6-E6-F6 -> 593.3485 | H6: =H5+G6 -> -2568.0045
A7: ="M"&4 -> M4 | B7: ='04_Production Ramp'!C8 -> 1300 | C7: ='03_Sales Mix'!D12 -> 5.655 | D7: =B7*C7 -> 7351.5 | E7: =B7*'02_Unit Economics'!$D$12 -> 1968.2 | F7: ='05_OPEX Monthly'!C19 -> 3133.5515 | G7: =D7-E7-F7 -> 2249.7485 | H7: =H6+G7 -> -318.256
A8: ="M"&5 -> M5 | B8: ='04_Production Ramp'!C9 -> 1500 | C8: ='03_Sales Mix'!D12 -> 5.655 | D8: =B8*C8 -> 8482.5 | E8: =B8*'02_Unit Economics'!$D$12 -> 2271 | F8: ='05_OPEX Monthly'!C19 -> 3133.5515 | G8: =D8-E8-F8 -> 3077.9485 | H8: =H7+G8 -> 2759.6925
A9: ="M"&6 -> M6 | B9: ='04_Production Ramp'!C10 -> 1800 | C9: ='03_Sales Mix'!D12 -> 5.655 | D9: =B9*C9 -> 10179 | E9: =B9*'02_Unit Economics'!$D$12 -> 2725.2 | F9: ='05_OPEX Monthly'!C19 -> 3133.5515 | G9: =D9-E9-F9 -> 4320.2485 | H9: =H8+G9 -> 7079.941
A10: ="M"&7 -> M7 | B10: ='04_Production Ramp'!C11 -> 2200 | C10: ='03_Sales Mix'!D12 -> 5.655 | D10: =B10*C10 -> 12441 | E10: =B10*'02_Unit Economics'!$D$12 -> 3330.8 | F10: ='05_OPEX Monthly'!C19 -> 3133.5515 | G10: =D10-E10-F10 -> 5976.6485 | H10: =H9+G10 -> 13056.59
A11: ="M"&8 -> M8 | B11: ='04_Production Ramp'!C12 -> 2500 | C11: ='03_Sales Mix'!D12 -> 5.655 | D11: =B11*C11 -> 14137.5 | E11: =B11*'02_Unit Economics'!$D$12 -> 3785 | F11: ='05_OPEX Monthly'!C19 -> 3133.5515 | G11: =D11-E11-F11 -> 7218.9485 | H11: =H10+G11 -> 20275.538
A12: ="M"&9 -> M9 | B12: ='04_Production Ramp'!C13 -> 2800 | C12: ='03_Sales Mix'!D12 -> 5.655 | D12: =B12*C12 -> 15834 | E12: =B12*'02_Unit Economics'!$D$12 -> 4239.2 | F12: ='05_OPEX Monthly'!C19 -> 3133.5515 | G12: =D12-E12-F12 -> 8461.2485 | H12: =H11+G12 -> 28736.786
A13: ="M"&10 -> M10 | B13: ='04_Production Ramp'!C14 -> 3050 | C13: ='03_Sales Mix'!D12 -> 5.655 | D13: =B13*C13 -> 17247.75 | E13: =B13*'02_Unit Economics'!$D$12 -> 4617.7 | F13: ='05_OPEX Monthly'!C19 -> 3133.5515 | G13: =D13-E13-F13 -> 9496.4985 | H13: =H12+G13 -> 38233.285
A14: ="M"&11 -> M11 | B14: ='04_Production Ramp'!C15 -> 3250 | C14: ='03_Sales Mix'!D12 -> 5.655 | D14: =B14*C14 -> 18378.75 | E14: =B14*'02_Unit Economics'!$D$12 -> 4920.5 | F14: ='05_OPEX Monthly'!C19 -> 3133.5515 | G14: =D14-E14-F14 -> 10324.699 | H14: =H13+G14 -> 48557.984
A15: ="M"&12 -> M12 | B15: ='04_Production Ramp'!C16 -> 3500 | C15: ='03_Sales Mix'!D12 -> 5.655 | D15: =B15*C15 -> 19792.5 | E15: =B15*'02_Unit Economics'!$D$12 -> 5299 | F15: ='05_OPEX Monthly'!C19 -> 3133.5515 | G15: =D15-E15-F15 -> 11359.949 | H15: =H14+G15 -> 59917.932
A16: Год 1 ИТОГО | B16: =SUM(B4:B15) -> 23550 | D16: =SUM(D4:D15) -> 133175.25 | E16: =SUM(E4:E15) -> 35654.7 | F16: =SUM(F4:F15) -> 37602.618 | G16: =SUM(G4:G15) -> 59917.932 | H16: =H15 -> 59917.932

Sheet 09_PL Суперопт
A1: P&L 12 МЕСЯЦЕВ — СУПЕР-ОПТИМИСТИЧЕСКИЙ
A3: Месяц | B3: Кг/мес | C3: Ср.цена €/кг | D3: Выручка € | E3: Variable cost € | F3: OPEX € | G3: EBITDA € | H3: Накоп. EBITDA €
A4: ="M"&1 -> M1 | B4: ='04_Production Ramp'!D5 -> 500 | C4: ='03_Sales Mix'!E12 -> 5.125 | D4: =B4*C4 -> 2562.5 | E4: =B4*'02_Unit Economics'!$D$12 -> 757 | F4: ='05_OPEX Monthly'!D19 -> 2163.5515 | G4: =D4-E4-F4 -> -358.0515 | H4: =G4 -> -358.0515
A5: ="M"&2 -> M2 | B5: ='04_Production Ramp'!D6 -> 900 | C5: ='03_Sales Mix'!E12 -> 5.125 | D5: =B5*C5 -> 4612.5 | E5: =B5*'02_Unit Economics'!$D$12 -> 1362.6 | F5: ='05_OPEX Monthly'!D19 -> 2163.5515 | G5: =D5-E5-F5 -> 1086.3485 | H5: =H4+G5 -> 728.297
A6: ="M"&3 -> M3 | B6: ='04_Production Ramp'!D7 -> 1500 | C6: ='03_Sales Mix'!E12 -> 5.125 | D6: =B6*C6 -> 7687.5 | E6: =B6*'02_Unit Economics'!$D$12 -> 2271 | F6: ='05_OPEX Monthly'!D19 -> 2163.5515 | G6: =D6-E6-F6 -> 3252.9485 | H6: =H5+G6 -> 3981.2455
A7: ="M"&4 -> M4 | B7: ='04_Production Ramp'!D8 -> 2200 | C7: ='03_Sales Mix'!E12 -> 5.125 | D7: =B7*C7 -> 11275 | E7: =B7*'02_Unit Economics'!$D$12 -> 3330.8 | F7: ='05_OPEX Monthly'!D19 -> 2163.5515 | G7: =D7-E7-F7 -> 5780.6485 | H7: =H6+G7 -> 9761.894
A8: ="M"&5 -> M5 | B8: ='04_Production Ramp'!D9 -> 2800 | C8: ='03_Sales Mix'!E12 -> 5.125 | D8: =B8*C8 -> 14350 | E8: =B8*'02_Unit Economics'!$D$12 -> 4239.2 | F8: ='05_OPEX Monthly'!D19 -> 2163.5515 | G8: =D8-E8-F8 -> 7947.2485 | H8: =H7+G8 -> 17709.143
A9: ="M"&6 -> M6 | B9: ='04_Production Ramp'!D10 -> 3500 | C9: ='03_Sales Mix'!E12 -> 5.125 | D9: =B9*C9 -> 17937.5 | E9: =B9*'02_Unit Economics'!$D$12 -> 5299 | F9: ='05_OPEX Monthly'!D19 -> 2163.5515 | G9: =D9-E9-F9 -> 10474.949 | H9: =H8+G9 -> 28184.091
A10: ="M"&7 -> M7 | B10: ='04_Production Ramp'!D11 -> 4200 | C10: ='03_Sales Mix'!E12 -> 5.125 | D10: =B10*C10 -> 21525 | E10: =B10*'02_Unit Economics'!$D$12 -> 6358.8 | F10: ='05_OPEX Monthly'!D19 -> 2163.5515 | G10: =D10-E10-F10 -> 13002.648 | H10: =H9+G10 -> 41186.74
A11: ="M"&8 -> M8 | B11: ='04_Production Ramp'!D12 -> 4800 | C11: ='03_Sales Mix'!E12 -> 5.125 | D11: =B11*C11 -> 24600 | E11: =B11*'02_Unit Economics'!$D$12 -> 7267.2 | F11: ='05_OPEX Monthly'!D19 -> 2163.5515 | G11: =D11-E11-F11 -> 15169.248 | H11: =H10+G11 -> 56355.988
A12: ="M"&9 -> M9 | B12: ='04_Production Ramp'!D13 -> 5400 | C12: ='03_Sales Mix'!E12 -> 5.125 | D12: =B12*C12 -> 27675 | E12: =B12*'02_Unit Economics'!$D$12 -> 8175.6 | F12: ='05_OPEX Monthly'!D19 -> 2163.5515 | G12: =D12-E12-F12 -> 17335.849 | H12: =H11+G12 -> 73691.837
A13: ="M"&10 -> M10 | B13: ='04_Production Ramp'!D14 -> 5800 | C13: ='03_Sales Mix'!E12 -> 5.125 | D13: =B13*C13 -> 29725 | E13: =B13*'02_Unit Economics'!$D$12 -> 8781.2 | F13: ='05_OPEX Monthly'!D19 -> 2163.5515 | G13: =D13-E13-F13 -> 18780.249 | H13: =H12+G13 -> 92472.085
A14: ="M"&11 -> M11 | B14: ='04_Production Ramp'!D15 -> 6000 | C14: ='03_Sales Mix'!E12 -> 5.125 | D14: =B14*C14 -> 30750 | E14: =B14*'02_Unit Economics'!$D$12 -> 9084 | F14: ='05_OPEX Monthly'!D19 -> 2163.5515 | G14: =D14-E14-F14 -> 19502.448 | H14: =H13+G14 -> 111974.53
A15: ="M"&12 -> M12 | B15: ='04_Production Ramp'!D16 -> 6200 | C15: ='03_Sales Mix'!E12 -> 5.125 | D15: =B15*C15 -> 31775 | E15: =B15*'02_Unit Economics'!$D$12 -> 9386.8 | F15: ='05_OPEX Monthly'!D19 -> 2163.5515 | G15: =D15-E15-F15 -> 20224.648 | H15: =H14+G15 -> 132199.18
A16: Год 1 ИТОГО | B16: =SUM(B4:B15) -> 43800 | D16: =SUM(D4:D15) -> 224475 | E16: =SUM(E4:E15) -> 66313.2 | F16: =SUM(F4:F15) -> 25962.618 | G16: =SUM(G4:G15) -> 132199.18 | H16: =H15 -> 132199.18

Sheet 10_Break-even
A1: BREAK-EVEN ANALYSIS — точка безубыточности по 3 сценариям
A3: Параметр | B3: Пессимизм | C3: Реализм | D3: Супер-опт
A4: Variable cost €/кг | B4: ='02_Unit Economics'!$D$12 -> 1.514 | C4: ='02_Unit Economics'!$D$12 -> 1.514 | D4: ='02_Unit Economics'!$D$12 -> 1.514
A5: Средневзвешенная цена €/кг | B5: ='03_Sales Mix'!C12 -> 6.125 | C5: ='03_Sales Mix'!D12 -> 5.655 | D5: ='03_Sales Mix'!E12 -> 5.125
A6: Маржа €/кг (price - VC) | B6: =B5-B4 -> 4.611 | C6: =C5-C4 -> 4.141 | D6: =D5-D4 -> 3.611
A7: OPEX €/мес | B7: ='05_OPEX Monthly'!B19 -> 4245.8015 | C7: ='05_OPEX Monthly'!C19 -> 3133.5515 | D7: ='05_OPEX Monthly'!D19 -> 2163.5515
A8: Break-even кг/мес | B8: =B7/B6 -> 920.79842 | C8: =C7/C6 -> 756.71372 | D8: =D7/D6 -> 599.15577
A9: Break-even кг/день (26 раб.д) | B9: =B8/26 -> 35.415324 | C9: =C8/26 -> 29.104374 | D9: =D8/26 -> 23.044453
A10: Break-even выручка €/мес | B10: =B8*B5 -> 5639.8903 | C10: =C8*C5 -> 4279.2161 | D10: =D8*D5 -> 3070.6733

Sheet 11_Cash Flow
A1: CASH FLOW — 12 МЕСЯЦЕВ (3 сценария)
A3: Месяц | B3: EBITDA ПЕССИМ | C3: Кум.ПЕССИМ | D3: EBITDA РЕАЛИЗМ | E3: Кум.РЕАЛИЗМ | F3: EBITDA СУПЕР | G3: Кум.СУПЕР
A4: M0 (старт после CAPEX) | C4: =-'06_CAPEX'!B15 -> -24414.25 | E4: =-'06_CAPEX'!B15 -> -24414.25 | G4: =-'06_CAPEX'!B15 -> -24414.25
A5: ="M"&1 -> M1 | B5: ='07_PL Пессимизм'!G4 -> -3554.1515 | C5: =C4+B5 -> -27968.401 | D5: ='08_PL Реализм'!G4 -> -2098.3015 | E5: =E4+D5 -> -26512.552 | F5: ='09_PL Суперопт'!G4 -> -358.0515 | G5: =G4+F5 -> -24772.302
A6: ="M"&2 -> M2 | B6: ='07_PL Пессимизм'!G5 -> -2862.5015 | C6: =C5+B6 -> -30830.903 | D6: ='08_PL Реализм'!G5 -> -1063.0515 | E6: =E5+D6 -> -27575.603 | F6: ='09_PL Суперопт'!G5 -> 1086.3485 | G6: =G5+F6 -> -23685.953
A7: ="M"&3 -> M3 | B7: ='07_PL Пессимизм'!G6 -> -1940.3015 | C7: =C6+B7 -> -32771.204 | D7: ='08_PL Реализм'!G6 -> 593.3485 | E7: =E6+D7 -> -26982.254 | F7: ='09_PL Суперопт'!G6 -> 3252.9485 | G7: =G6+F7 -> -20433.004
A8: ="M"&4 -> M4 | B8: ='07_PL Пессимизм'!G7 -> -1018.1015 | C8: =C7+B8 -> -33789.306 | D8: ='08_PL Реализм'!G7 -> 2249.7485 | E8: =E7+D8 -> -24732.506 | F8: ='09_PL Суперопт'!G7 -> 5780.6485 | G8: =G7+F8 -> -14652.356
A9: ="M"&5 -> M5 | B9: ='07_PL Пессимизм'!G8 -> -95.9015 | C9: =C8+B9 -> -33885.207 | D9: ='08_PL Реализм'!G8 -> 3077.9485 | E9: =E8+D9 -> -21654.557 | F9: ='09_PL Суперопт'!G8 -> 7947.2485 | G9: =G8+F9 -> -6705.1075
A10: ="M"&6 -> M6 | B10: ='07_PL Пессимизм'!G9 -> 826.2985 | C10: =C9+B10 -> -33058.909 | D10: ='08_PL Реализм'!G9 -> 4320.2485 | E10: =E9+D10 -> -17334.309 | F10: ='09_PL Суперопт'!G9 -> 10474.949 | G10: =G9+F10 -> 3769.841
A11: ="M"&7 -> M7 | B11: ='07_PL Пессимизм'!G10 -> 1748.4985 | C11: =C10+B11 -> -31310.411 | D11: ='08_PL Реализм'!G10 -> 5976.6485 | E11: =E10+D11 -> -11357.66 | F11: ='09_PL Суперопт'!G10 -> 13002.648 | G11: =G10+F11 -> 16772.489
A12: ="M"&8 -> M8 | B12: ='07_PL Пессимизм'!G11 -> 2670.6985 | C12: =C11+B12 -> -28639.712 | D12: ='08_PL Реализм'!G11 -> 7218.9485 | E12: =E11+D12 -> -4138.712 | F12: ='09_PL Суперопт'!G11 -> 15169.248 | G12: =G11+F12 -> 31941.738
A13: ="M"&9 -> M9 | B13: ='07_PL Пессимизм'!G12 -> 3592.8985 | C13: =C12+B13 -> -25046.814 | D13: ='08_PL Реализм'!G12 -> 8461.2485 | E13: =E12+D13 -> 4322.5365 | F13: ='09_PL Суперопт'!G12 -> 17335.849 | G13: =G12+F13 -> 49277.586
A14: ="M"&10 -> M10 | B14: ='07_PL Пессимизм'!G13 -> 4284.5485 | C14: =C13+B14 -> -20762.265 | D14: ='08_PL Реализм'!G13 -> 9496.4985 | E14: =E13+D14 -> 13819.035 | F14: ='09_PL Суперопт'!G13 -> 18780.249 | G14: =G13+F14 -> 68057.835
A15: ="M"&11 -> M11 | B15: ='07_PL Пессимизм'!G14 -> 4745.6485 | C15: =C14+B15 -> -16016.617 | D15: ='08_PL Реализм'!G14 -> 10324.699 | E15: =E14+D15 -> 24143.733 | F15: ='09_PL Суперопт'!G14 -> 19502.448 | G15: =G14+F15 -> 87560.284
A16: ="M"&12 -> M12 | B16: ='07_PL Пессимизм'!G15 -> 4976.1985 | C16: =C15+B16 -> -11040.418 | D16: ='08_PL Реализм'!G15 -> 11359.949 | E16: =E15+D16 -> 35503.682 | F16: ='09_PL Суперопт'!G15 -> 20224.648 | G16: =G15+F16 -> 107784.93

Sheet 12_Sensitivity
A1: SENSITIVITY — что если цены/объёмы изменятся
A3: БАЗОВЫЙ СЦЕНАРИЙ = РЕАЛИЗМ (год 1)
A5: Параметр | B5: Базовое значение | C5: Эффект на год 1 EBITDA
A6: Мука +20% | B6: ='01_Inputs'!C4*1.2 -> 0.9 | C6: Снизит маржу на ~€0,11/кг
A7: Мука −10% | B7: ='01_Inputs'!C4*0.9 -> 0.675 | C7: Повысит маржу на ~€0,05/кг
A8: Цена ОПТ-канала +5% | B8: =' 02_unit economics'!b16*1.05 -> #NAME? | C8: Повысит ср.цену в опт-mix
A9: Объём год 1 −20% | B9: ='04_Production Ramp'!C17*0.8 -> 18840 | C9: Линейно EBITDA вниз
A10: Объём год 1 +20% | B10: ='04_Production Ramp'!C17*1.2 -> 28260 | C10: Линейно EBITDA вверх
A11: Третий работник с M7 | B11: ='01_Inputs'!C13*1.3215 -> 1613.5515 | C11: +€1 614/мес OPEX начиная с M7
A12: Электричество +50% | B12: ='01_Inputs'!C8*1.5 -> 0.18 | C12: +€250/мес OPEX
A13: Halal-канал даёт +30% объёма | B13: 1.30 | C13: Если активирован M3, не M6

Sheet 14_Sources
A1: СПИСОК ИСТОЧНИКОВ
A3: Категория | B3: Источник | C3: URL / Контакт
A4: Регулирование | B4: BOE-A-2025-3950 (IVA 4% на лаваш) | C4: https://www.boe.es/buscar/doc.php?id=BOE-A-2025-3950
A5: Регулирование | B5: BOE-A-2026-3815 (SMI 2026) | C5: https://www.boe.es
A6: Регулирование | B6: Real Decreto 308/2019 (clasificación pan) | C6: https://www.boe.es
A7: Регулирование | B7: Reglamento UE 1169/2011 (этикетка) | C7: https://eur-lex.europa.eu
A8: Регулирование | B8: Gencat Salut Pública (RSIPAC) | C8: https://salutpublica.gencat.cat
A9: Регулирование | B9: AESAN (RGSEAA) | C9: https://www.aesan.gob.es
A10: Энергия | B10: Roams Energía (PYME tariffs) | C10: https://roams.es/energia/luz/tarifas-luz-empresas/
A11: Энергия | B11: TarifaLuzHora (PVPC) | C11: https://tarifaluzhora.es
A12: Энергия | B12: Eni Plenitude (gas TUR) | C12: https://eniplenitude.es/blog/energia/precio-gas-natural-kwh/
A13: Энергия | B13: Maeswell обrador baseline | C13: https://app.maeswell.com
A14: Сырьё | B14: B-Grup Distribuciones (мука) | C14: https://www.bgrup.es
... A34: Каналы | B34: Just Eat для бизнеса | C34: https://restaurantes.just-eat.es
